{
	"owner": "881377",
	"uid": "881377-881377-d07b4fbd-2b31-4996-820c-5f2b3f7fad48",
	"foldersOrder": [],
	"variables": [],
	"id": "881377-d07b4fbd-2b31-4996-820c-5f2b3f7fad48",
	"name": "--- On Developds ---",
	"description": null,
	"order": [
		"e95b3d4e-e09a-4e94-9447-725d71e87027",
		"9fddd688-913e-450b-8776-93fadb6ab745"
	],
	"folders_order": [],
	"auth": null,
	"protocolProfileBehavior": {},
	"createdAt": "2022-08-02T08:16:52.000Z",
	"events": null,
	"options": {
		"type": "readWrite"
	},
	"folders": [],
	"requests": [
		{
			"owner": "881377",
			"uid": "881377-e95b3d4e-e09a-4e94-9447-725d71e87027",
			"id": "e95b3d4e-e09a-4e94-9447-725d71e87027",
			"name": "this is req 2",
			"description": "",
			"method": "GET",
			"data": null,
			"dataOptions": null,
			"dataMode": null,
			"headerData": null,
			"folder": "",
			"collection": "881377-d07b4fbd-2b31-4996-820c-5f2b3f7fad48",
			"auth": null,
			"queryParams": null,
			"pathVariableData": null,
			"url": "",
			"protocolProfileBehavior": {},
			"createdAt": null,
			"events": null,
			"responses_order": [],
			"responses": []
		},
		{
			"owner": "881377",
			"uid": "881377-9fddd688-913e-450b-8776-93fadb6ab745",
			"id": "9fddd688-913e-450b-8776-93fadb6ab745",
			"name": "New Requestdasdas",
			"description": "",
			"method": "GET",
			"data": null,
			"dataOptions": null,
			"dataMode": null,
			"headerData": null,
			"folder": "",
			"collection": "881377-d07b4fbd-2b31-4996-820c-5f2b3f7fad48",
			"auth": null,
			"queryParams": null,
			"pathVariableData": null,
			"url": "",
			"protocolProfileBehavior": {},
			"createdAt": null,
			"events": null,
			"responses_order": [],
			"responses": []
		}
	]
}